src/__init__.py
src/cert.py
SSL_Generator_Validator-0.1.dist-info/LICENCE
SSL_Generator_Validator-0.1.dist-info/METADATA
SSL_Generator_Validator-0.1.dist-info/WHEEL
SSL_Generator_Validator-0.1.dist-info/top_level.txt
SSL_Generator_Validator-0.1.dist-info/RECORD
